gospel/__init__.py
gospel/__main__.py
gospel/gospel_message.py
gospel-0.0.3.dist-info/METADATA
gospel-0.0.3.dist-info/WHEEL
gospel-0.0.3.dist-info/entry_points.txt
gospel-0.0.3.dist-info/top_level.txt
gospel-0.0.3.dist-info/RECORD
